dzbee/__init__.py
dzbee/__main__.py
dzbee/cmat2html.py
dzbee/color_map.py
dzbee/common_prefix.py
dzbee/detect.py
dzbee/dzbee.py
dzbee/gen_cmat.py
dzbee/gen_filename.py
dzbee/gen_pairs.py
dzbee/loadtext.py
dzbee/save_xlsx_tsv_csv.py
dzbee/text2lists.py
dzbee-0.1.1a3.dist-info/entry_points.txt
dzbee-0.1.1a3.dist-info/LICENSE
dzbee-0.1.1a3.dist-info/WHEEL
dzbee-0.1.1a3.dist-info/METADATA
dzbee-0.1.1a3.dist-info/RECORD
