Metadata-Version: 2.1
Name: dzbee
Version: 0.1.1a3
Summary: pack_name descr 
Home-page: https://github.com/ffreemt/dzbee
License: MIT
Author: ffreemt
Requires-Python: >=3.8.3,<4.0.0
Classifier: License :: OSI Approved :: MIT License
Classifier: Programming Language :: Python :: 3
Classifier: Programming Language :: Python :: 3.10
Classifier: Programming Language :: Python :: 3.9
Provides-Extra: plot
Requires-Dist: Jinja2 (>=3.1.2,<4.0.0)
Requires-Dist: Morfessor (>=2.0.6,<3.0.0)
Requires-Dist: XlsxWriter (>=3.0.3,<4.0.0)
Requires-Dist: aset2pairs (>=0.1.0,<0.2.0)
Requires-Dist: cchardet (>=2.1.7,<3.0.0)
Requires-Dist: holoviews (>=1.14.9,<2.0.0); extra == "plot"
Requires-Dist: icecream (>=2.1.1,<3.0.0)
Requires-Dist: install (>=1.3.5,<2.0.0)
Requires-Dist: json-de2zh (>=0.1.1,<0.2.0)
Requires-Dist: logzero (>=1.7.0,<2.0.0)
Requires-Dist: plotly (>=5.8.0,<6.0.0); extra == "plot"
Requires-Dist: polyglot (>=16.7.4,<17.0.0)
Requires-Dist: seaborn (>=0.11.2,<0.12.0); extra == "plot"
Requires-Dist: typer (>=0.4.1,<0.5.0)
Project-URL: Repository, https://github.com/ffreemt/dzbee
